pyfunc_ensembler_runner/__init__.py
pyfunc_ensembler_runner/__main__.py
pyfunc_ensembler_runner/ensembler_runner.py
pyfunc_ensembler_runner/handler.py
pyfunc_ensembler_runner/server.py
tests/__init__.py
tests/conftest.py
tests/test_ensembler_runner.py
naufal_pyfunc_ensembler_service_2-1.21.2.dev23.dist-info/METADATA
naufal_pyfunc_ensembler_service_2-1.21.2.dev23.dist-info/WHEEL
naufal_pyfunc_ensembler_service_2-1.21.2.dev23.dist-info/top_level.txt
naufal_pyfunc_ensembler_service_2-1.21.2.dev23.dist-info/RECORD
